compas_rv/__init__.py
compas_rv/__main__.py
compas_rv/commands.py
compas_rv/session.py
compas_rv/settings.py
compas_rv/conduits/__init__.py
compas_rv/conduits/edgesconduit.py
compas_rv/conduits/horizontalconduit.py
compas_rv/datastructures/__init__.py
compas_rv/datastructures/diagram.py
compas_rv/datastructures/forcediagram.py
compas_rv/datastructures/formdiagram.py
compas_rv/datastructures/pattern.py
compas_rv/datastructures/subdmesh.py
compas_rv/datastructures/thrustdiagram.py
compas_rv/patterns/__init__.py
compas_rv/patterns/circular.py
compas_rv/patterns/rectangular.py
compas_rv/scene/__init__.py
compas_rv/scene/diagramobject.py
compas_rv/scene/forceobject.py
compas_rv/scene/formobject.py
compas_rv/scene/patternobject.py
compas_rv/scene/thrustobject.py
compas_rv/solvers/__init__.py
compas_rv/solvers/forcefromform.py
compas_rv/solvers/scalehorizonal.py
compas_rv-0.9.5.dist-info/licenses/AUTHORS.md
compas_rv-0.9.5.dist-info/licenses/LICENSE
compas_rv-0.9.5.dist-info/METADATA
compas_rv-0.9.5.dist-info/WHEEL
compas_rv-0.9.5.dist-info/top_level.txt
compas_rv-0.9.5.dist-info/RECORD
