Metadata-Version: 2.4
Name: compas_rv
Version: 0.9.5
Summary: COMPAS RhinoVAULT
Author-email: tom van mele <tom.v.mele@gmail.com>
License: MIT License
Project-URL: Homepage, https://blockresearchgroup.github.io/compas_rv
Project-URL: Documentation, https://blockresearchgroup.github.io/compas_rv
Project-URL: Repository, https://github.com/blockresearchgroup/compas_rv
Project-URL: Changelog, https://github.com/blockresearchgroup/compas_rv/blob/main/CHANGELOG.md
Project-URL: Issues, https://github.com/blockresearchgroup/compas_rv/issues
Project-URL: Forum, https://forum.compas-framework.org/
Classifier: Development Status :: 4 - Beta
Classifier: Topic :: Scientific/Engineering
Classifier: Operating System :: Unix
Classifier: Operating System :: POSIX
Classifier: Operating System :: Microsoft :: Windows
Classifier: Programming Language :: Python
Classifier: Programming Language :: Python :: 3
Classifier: Programming Language :: Python :: 3.9
Requires-Python: >=3.9
License-File: LICENSE
License-File: AUTHORS.md
Requires-Dist: compas>=2.13
Requires-Dist: compas_cgal>=0.9.1
Requires-Dist: compas_dem>=0.3.3
Requires-Dist: compas_libigl>=0.7.4
Requires-Dist: compas_rui>=0.5.1
Requires-Dist: compas_session>=0.5.5
Requires-Dist: compas_skeleton
Requires-Dist: compas_tna>=0.5
Requires-Dist: compas_triangle>=1.2.1
Requires-Dist: tessagon
Provides-Extra: dev
Requires-Dist: attrs>=17.4; extra == "dev"
Requires-Dist: black>=22.12.0; extra == "dev"
Requires-Dist: bump-my-version; extra == "dev"
Requires-Dist: compas_invocations2; extra == "dev"
Requires-Dist: invoke>=0.14; extra == "dev"
Requires-Dist: ruff; extra == "dev"
Requires-Dist: sphinx_compas2_theme; extra == "dev"
Requires-Dist: twine; extra == "dev"
Requires-Dist: wheel; extra == "dev"
Dynamic: license-file
